{
  "meta": {
    "source_path": "D:\\기계도면\\기계도면\\14. 비산재 처리설비 (조선내화E)\\비산재 준공도서\\비산재(기계)\\16. 운전 및 유지관리 지침서(●)\\16. 운전 및 유지관리 지침서.pdf",
    "company_id": "14",
    "company_name": "비산재 처리설비",
    "equipment": "비산재처리",
    "doc_type": "MANUAL",
    "rev": "AS_BUILT",
    "is_latest": true,
    "extracted_at": "2026-03-27T20:18:19",
    "chunk_count": 20,
    "vision_pages": 0
  },
  "chunks": [
    {
      "chunk_idx": 1,
      "text": "16. 운전 및 유지관리 지침서\n0 2019.11. AS-BUILT B.H.JEONG J.S.LIM H.S.KIM\n개정번호 일자 내용 작 성 자 검 토 자 승 인 자\n공사명 : 제주환경자원순환센터(소각시설) 조성공사 도 서 명 : 운전 및 유지관리 지침서\n분 야 : 폐기물 및 기계분야 도서 번호 : JJ-M-VP-009-16\n품 명 : 비산재 처리설비 도서 상태 : AS-BUILT\n제작사명: (주)조선내화이엔지 작 성 일 : 2019년 11월",
      "header": "16. 운전 및 유지관리 지침서",
      "section_type": "운전",
      "equipment": [
        "비산재처리"
      ],
      "company_id": "14",
      "company_name": "비산재 처리설비",
      "source_file": "16. 운전 및 유지관리 지침서",
      "source_path": "D:\\기계도면\\기계도면\\14. 비산재 처리설비 (조선내화E)\\비산재 준공도서\\비산재(기계)\\16. 운전 및 유지관리 지침서(●)\\16. 운전 및 유지관리 지침서.pdf",
      "rev": "AS_BUILT",
      "chunk_hash": "bd3291ddf34942e9",
      "char_count": 249
    },
    {
      "chunk_idx": 2,
      "text": "J-M-VP-009-16\n품 명 : 비산재 처리설비 도서 상태 : AS-BUILT\n제작사명: (주)조선내화이엔지 작 성 일 : 2019년 11월 INDEX\nGS 건설 1 OF 11\n1.0 운 전 요 령\n2.0 보 수 요 령\n3.0 유지보수요령\n4.0 트러블의(TROUBLE)처리요령\n1/11",
      "header": "INDEX",
      "section_type": "점검",
      "equipment": [
        "비산재처리"
      ],
      "company_id": "14",
      "company_name": "비산재 처리설비",
      "source_file": "16. 운전 및 유지관리 지침서",
      "source_path": "D:\\기계도면\\기계도면\\14. 비산재 처리설비 (조선내화E)\\비산재 준공도서\\비산재(기계)\\16. 운전 및 유지관리 지침서(●)\\16. 운전 및 유지관리 지침서.pdf",
      "rev": "AS_BUILT",
      "chunk_hash": "52db4aaad557fea0",
      "char_count": 162
    },
    {
      "chunk_idx": 3,
      "text": "NDEX\nGS 건설 1 OF 11\n1.0 운 전 요 령\n2.0 보 수 요 령\n3.0 유지보수요령\n4.0 트러블의(TROUBLE)처리요령\n1/11",
      "header": "CUSTOMER SHEET NO",
      "section_type": "점검",
      "equipment": [
        "비산재처리"
      ],
      "company_id": "14",
      "company_name": "비산재 처리설비",
      "source_file": "16. 운전 및 유지관리 지침서",
      "source_path": "D:\\기계도면\\기계도면\\14. 비산재 처리설비 (조선내화E)\\비산재 준공도서\\비산재(기계)\\16. 운전 및 유지관리 지침서(●)\\16. 운전 및 유지관리 지침서.pdf",
      "rev": "AS_BUILT",
      "chunk_hash": "0588d626c157c634",
      "char_count": 80
    },
    {
      "chunk_idx": 4,
      "text": "NDEX\nGS 건설 1 OF 11\n1.0 운 전 요 령\n2.0 보 수 요 령\n3.0 유지보수요령\n4.0 트러블의(TROUBLE)처리요령\n1/11 CUSTOMER SHEET NO\n운전 및 유지보수 지침서\nGS 건설 2 OF 11\n1.0 운 전 요 령\n수송물을 운반하기 전에 콘베어(CONVEYOR)를 무부하 상태에서 시운전 합니다. 이때 물론 기초 부문의\n콘크리트(CONCRETE)가 충분히 굳은 다음이라야 합니다.\n시운전을 시작하기 전에 다음 순서로 점검을 하고, 그 준비가 충분한가를 확인후에 시운전을 해주시기\n바랍니다.\n1.1 테이크 업의 조정\n테이크 업(TAKE-UP)은 체인(CHAIN)의 장력을 조정하기 위한 것입니다.\n테이크 업은 스트로크 범위내로 장력 흡수가 가능해야 하므로 정확히 조정해야 합니다. 너무 잡아당기면\n체인에 지나친 장력을 주어 체인의 수명을 단축 시킵니다. 반면에 너무 느슨하면 헤드 스프로켓\n(HEAD SPROCKET)의 뒤쪽에서 체인이 늘어져 고장의 원인이 됩니다.\n1.2 각부의 연결상태 재 확인\n시운전을 시작하기 전에 연결 및 고정 볼트(BOLT)의 조립 상태를 다시 확인해 주십시오. 애써 설치한\n콘베어의 일부 볼트가 풀어져 있는 상태로 시운전을 하여 중심이 흐트러지는 경우가 있습니다.\n1.3 케이스 내부의 청소\n케이스 설치시 사용된 도구 또는 보강재 등이 방치 되어 있는경우가 있습니다. 그대로 운전하면 콘베어에\n끼어들어 고장을 일으키므로 완전히 제거해주시기 바랍니다.\n1.4 급 유\n감속기나 전동 체인 등에는 지정된 윤활유를 지정된 양 만큼 급유해 주십시오.\n베어링 유니트(BEARING UNIT)에는 공장에서 그리이스(GREASE)를 주입 했으나 다시 한번 주유 여부를\n확인해 주십시오. 또한 싸이크로 모터(CYCLO MOTOR)에는 지정된 윤활유를 지정된 양만큼 급유하시기\n바랍니다.\n1.5 안전 확인\n콘 베어는 전체를 볼 수가 없을때가 많습니다. 도중에 콘베어 속에 손을 넣고 있는 사람이 있는 상태에서\n스위치(SWITCH)를 넣게 되면 안전사고가 일어나게 됩니다. 따라서 콘베어의 각 부분을 볼 수 있을 만큼의\n원인을 배치해서 작업상황을 잘 연락하여 안전을 확인한 후 스위치를 넣어야 합니다.\n1.6 무부하 시운전\n스위치(SWITCH)를 넣을때에 처음에는 두세번, 2초쯤 간격을 두어 스위치를 넣어 이상의 유무를\n확인하시기 바랍니다. 이상이 없으면 연속해서 운전합니다. 만약 시운전의 결과에 이상이 있으면\n5.0항의트러블(TROUBLE)처치 요령을 참고 하여 처리해 주시기 바랍니다.\n2/11",
      "header": "CUSTOMER SHEET NO",
      "section_type": "점검",
      "equipment": [
        "비산재처리"
      ],
      "company_id": "14",
      "company_name": "비산재 처리설비",
      "source_file": "16. 운전 및 유지관리 지침서",
      "source_path": "D:\\기계도면\\기계도면\\14. 비산재 처리설비 (조선내화E)\\비산재 준공도서\\비산재(기계)\\16. 운전 및 유지관리 지침서(●)\\16. 운전 및 유지관리 지침서.pdf",
      "rev": "AS_BUILT",
      "chunk_hash": "295351caa7416d39",
      "char_count": 1255
    },
    {
      "chunk_idx": 5,
      "text": "연속해서 운전합니다. 만약 시운전의 결과에 이상이 있으면\n5.0항의트러블(TROUBLE)처치 요령을 참고 하여 처리해 주시기 바랍니다.\n2/11 CUSTOMER SHEET NO\n운전 및 유지보수 지침서\nGS 건설 3 OF 11\n1.7 부하 시운전\n이상의 요령으로 무부하 시운전이 끝나면 다음은 부하 시운전을 합니다.\n수송물은 서서히 투입합니다. 또 투입 방법이 지정 되지 않을 경우, 연속 정량\n투입으로 생각해서 콘베어(CONVEYOR) 사양을 결정 하였습니다. 다음 표에\n시운전 결과를 기입해 두면 이후의 보수에 편리합니다.\n무 부하 운전시 부하 운전시\n전 압\n전 류\n전 력\n주축 회전수\n체인(CHAIN) 속도\n3/11",
      "header": "CUSTOMER SHEET NO",
      "section_type": "점검",
      "equipment": [
        "비산재처리"
      ],
      "company_id": "14",
      "company_name": "비산재 처리설비",
      "source_file": "16. 운전 및 유지관리 지침서",
      "source_path": "D:\\기계도면\\기계도면\\14. 비산재 처리설비 (조선내화E)\\비산재 준공도서\\비산재(기계)\\16. 운전 및 유지관리 지침서(●)\\16. 운전 및 유지관리 지침서.pdf",
      "rev": "AS_BUILT",
      "chunk_hash": "a713d83a22c5325d",
      "char_count": 347
    },
    {
      "chunk_idx": 6,
      "text": "전 결과를 기입해 두면 이후의 보수에 편리합니다.\n무 부하 운전시 부하 운전시\n전 압\n전 류\n전 력\n주축 회전수\n체인(CHAIN) 속도\n3/11 CUSTOMER SHEET NO\n운전 및 유지보수 지침서\nGS 건설 4 OF 11\n- 운전절차 (FLOW CHART)\n테이크업 조정은 되어 있는가? → 테이크업 조정",
      "header": "CUSTOMER SHEET NO",
      "section_type": "점검",
      "equipment": [
        "비산재처리"
      ],
      "company_id": "14",
      "company_name": "비산재 처리설비",
      "source_file": "16. 운전 및 유지관리 지침서",
      "source_path": "D:\\기계도면\\기계도면\\14. 비산재 처리설비 (조선내화E)\\비산재 준공도서\\비산재(기계)\\16. 운전 및 유지관리 지침서(●)\\16. 운전 및 유지관리 지침서.pdf",
      "rev": "AS_BUILT",
      "chunk_hash": "cc03c73072874c89",
      "char_count": 173
    },
    {
      "chunk_idx": 7,
      "text": "ET NO\n운전 및 유지보수 지침서\nGS 건설 4 OF 11\n- 운전절차 (FLOW CHART)\n테이크업 조정은 되어 있는가? → 테이크업 조정 NO\n↓",
      "header": "NO",
      "section_type": "점검",
      "equipment": [
        "비산재처리"
      ],
      "company_id": "14",
      "company_name": "비산재 처리설비",
      "source_file": "16. 운전 및 유지관리 지침서",
      "source_path": "D:\\기계도면\\기계도면\\14. 비산재 처리설비 (조선내화E)\\비산재 준공도서\\비산재(기계)\\16. 운전 및 유지관리 지침서(●)\\16. 운전 및 유지관리 지침서.pdf",
      "rev": "AS_BUILT",
      "chunk_hash": "ed372615f5a28bf5",
      "char_count": 85
    },
    {
      "chunk_idx": 8,
      "text": "YES\n각부의 연결은 잘되어있는가?\n→ BOLT 체결 또는 체인연결\nBOLT 및 체인",
      "header": "YES",
      "section_type": "일반",
      "equipment": [
        "비산재처리"
      ],
      "company_id": "14",
      "company_name": "비산재 처리설비",
      "source_file": "16. 운전 및 유지관리 지침서",
      "source_path": "D:\\기계도면\\기계도면\\14. 비산재 처리설비 (조선내화E)\\비산재 준공도서\\비산재(기계)\\16. 운전 및 유지관리 지침서(●)\\16. 운전 및 유지관리 지침서.pdf",
      "rev": "AS_BUILT",
      "chunk_hash": "14a83bcf048b17ac",
      "char_count": 47
    },
    {
      "chunk_idx": 10,
      "text": "YES\n케이스 내부의 이물질은 제거되어\n→ 케이스 내부청소\n있는가?",
      "header": "YES",
      "section_type": "청소",
      "equipment": [
        "비산재처리"
      ],
      "company_id": "14",
      "company_name": "비산재 처리설비",
      "source_file": "16. 운전 및 유지관리 지침서",
      "source_path": "D:\\기계도면\\기계도면\\14. 비산재 처리설비 (조선내화E)\\비산재 준공도서\\비산재(기계)\\16. 운전 및 유지관리 지침서(●)\\16. 운전 및 유지관리 지침서.pdf",
      "rev": "AS_BUILT",
      "chunk_hash": "999c529ca9845b76",
      "char_count": 37
    },
    {
      "chunk_idx": 12,
      "text": "YES\n급유는 잘 되어 있는가?\n→ 급유실시\n감속기,전동체인 베어링",
      "header": "YES",
      "section_type": "일반",
      "equipment": [
        "비산재처리"
      ],
      "company_id": "14",
      "company_name": "비산재 처리설비",
      "source_file": "16. 운전 및 유지관리 지침서",
      "source_path": "D:\\기계도면\\기계도면\\14. 비산재 처리설비 (조선내화E)\\비산재 준공도서\\비산재(기계)\\16. 운전 및 유지관리 지침서(●)\\16. 운전 및 유지관리 지침서.pdf",
      "rev": "AS_BUILT",
      "chunk_hash": "766f0fd1e4089c9a",
      "char_count": 37
    },
    {
      "chunk_idx": 19,
      "text": "CUSTOMER SHEET NO\n운전 및 유지보수 지침서\nGS 건설 5 OF 11\n↓",
      "header": "CUSTOMER SHEET NO",
      "section_type": "점검",
      "equipment": [
        "비산재처리"
      ],
      "company_id": "14",
      "company_name": "비산재 처리설비",
      "source_file": "16. 운전 및 유지관리 지침서",
      "source_path": "D:\\기계도면\\기계도면\\14. 비산재 처리설비 (조선내화E)\\비산재 준공도서\\비산재(기계)\\16. 운전 및 유지관리 지침서(●)\\16. 운전 및 유지관리 지침서.pdf",
      "rev": "AS_BUILT",
      "chunk_hash": "aa27942afcbaee3a",
      "char_count": 47
    },
    {
      "chunk_idx": 20,
      "text": "YES\n운반량에 따른 전류치를 측정하여\n기록유지한다.\n↓\n정지시\n운반물 투입을 정지한다. → 전원 OFF 금지",
      "header": "YES",
      "section_type": "정지",
      "equipment": [
        "비산재처리"
      ],
      "company_id": "14",
      "company_name": "비산재 처리설비",
      "source_file": "16. 운전 및 유지관리 지침서",
      "source_path": "D:\\기계도면\\기계도면\\14. 비산재 처리설비 (조선내화E)\\비산재 준공도서\\비산재(기계)\\16. 운전 및 유지관리 지침서(●)\\16. 운전 및 유지관리 지침서.pdf",
      "rev": "AS_BUILT",
      "chunk_hash": "2e1298ad90e61c22",
      "char_count": 61
    },
    {
      "chunk_idx": 23,
      "text": "CUSTOMER SHEET NO\n운전 및 유지보수 지침서\nGS 건설 6 OF 11\n2.0 보수요령\n콘베어(CONVEYOR)를 오래 효과적으로 사용하기 위해 아래와 같은 사항에 주의 하십시오.\n2.1 수송물의 투입방법\n운전을 시작할때는 수송물의 투입시점 및 방법에 충분히 주의하시기 바랍니다.\n플로우콘베어(FLOW CONVEYOR)는 보통 기동후 1~3초 정도 후에 정상운전에 들어가므로 그후에 투입을\n개시해 주십시오. 정상운전 전에 수송물을 투입하면 콘베어 체인에 과대한 힘이 걸려 모터(MOTOR)의\n기동이 안될 때가 있습니다.\n또 투입량은 필히 정량 투입을 해주시기 바랍니다. 투입량이 과대해지면 체인 (CHAIN)에 대한 충격력이\n커져 콘베어(CONVEYOR)에 불필요한 힘이 가해집니다.\n2.2 수송물의 잔량제거\n운전을 끝날때는 꼭 CASE내의 수송물을 완전히 배출 시킨후 중지 하십시오.(전설 비를 중지시킨 후 약\n5분간 공운전 시키면 충분합니다.)\n그 후 테일케이스(TAIL CASE)에 남은 수송물을 청소해 주시기 바랍니다.\n케이스(CASE)내에 수송물을 남겨두면 다음 운전에 큰 힘이 필요할뿐 아니라 수송물에\n부식성,고착성,부패성이 있으면 콘베어를 손상시키는 원인이 됩니다.\n6/11",
      "header": "CUSTOMER SHEET NO",
      "section_type": "시동",
      "equipment": [
        "비산재처리"
      ],
      "company_id": "14",
      "company_name": "비산재 처리설비",
      "source_file": "16. 운전 및 유지관리 지침서",
      "source_path": "D:\\기계도면\\기계도면\\14. 비산재 처리설비 (조선내화E)\\비산재 준공도서\\비산재(기계)\\16. 운전 및 유지관리 지침서(●)\\16. 운전 및 유지관리 지침서.pdf",
      "rev": "AS_BUILT",
      "chunk_hash": "b8fc8f9293b7da5d",
      "char_count": 614
    },
    {
      "chunk_idx": 24,
      "text": "내에 수송물을 남겨두면 다음 운전에 큰 힘이 필요할뿐 아니라 수송물에\n부식성,고착성,부패성이 있으면 콘베어를 손상시키는 원인이 됩니다.\n6/11 CUSTOMER SHEET NO\n운전 및 유지보수 지침서\nGS 건설 7 OF 11\n2.3 체인의 늘어남과 조정시기\n일반적으로 체인의 늘어남은 그림 11의 경향으로 진행하므로 가동 직후의 조정이 매우 중요합니다.\n따라서 다음의 구분을 참조해서 체인의 늘어남을 조정해 주시기 바랍니다.\n운전 개시 후 일주간 매일 1회\n그 후 1개월간 매주 2회\n그 후 매월 2회\n상기(上記) 조정은 1일 8시간 사용의 경우입니다. 만약 24시간 사용한다면 그만 큼 점검 간격을 짧게\n해주시기 바랍니다. 어느정도 지나면 체인의 늘어남은 거의 없어집니다.\n2.4 테이크업의 조정(SCREW TYPE인 경우)\n체인의 늘어남 조정은 테일 케이스에 취부된 자우 연동 나사식 테이크 업에 의해 실시해 주시기\n바랍니다.\n조정 방법에 대해서는 테일 케이스에 부착되어 있는 테이크 업 (TAKE-UP) 설명판을 참고하시기\n바랍니다. 테이크 업을 조정할 때는 먼저 콘베어가 정지 되어 있는 것을 확인하고 조정 하십 시오.\n조정후. 5분정도 무부하 운전을 하여 만약 체인에 큰 진동이 있으면 조정 나사를 1/4 회전시키면서 전후로\n돌려 체인의 장력을 다시 조절하십시오. 테이크 업은 체인의 늘어남을 흡수하여 체인에 적당한 장력을\n주는 작용을 하여 콘베어의 양호한 운전상태를 유지시키기 위한 장치 입니다.\n따라서 그 취급은 충분히 신중을 기하여 양호한 운전상태를 유지 시키기 위한 장 치 입니다. 따라서 그\n취급은 충분히 신중을 기하여 주시기 바랍니다. 또한 테일 후레임에 종축의 위치를 나타내는 표시를\n하여 조정시의 스트로크 (STROKE)량을 측정하여 표(3)과 같은 기록서를 작성해 두면 이후의 보수에\n편리 하므로 꼭 실시해 주시기 바랍니다.\n7/11",
      "header": "CUSTOMER SHEET NO",
      "section_type": "정지",
      "equipment": [
        "비산재처리"
      ],
      "company_id": "14",
      "company_name": "비산재 처리설비",
      "source_file": "16. 운전 및 유지관리 지침서",
      "source_path": "D:\\기계도면\\기계도면\\14. 비산재 처리설비 (조선내화E)\\비산재 준공도서\\비산재(기계)\\16. 운전 및 유지관리 지침서(●)\\16. 운전 및 유지관리 지침서.pdf",
      "rev": "AS_BUILT",
      "chunk_hash": "4e9ee7d34723b558",
      "char_count": 929
    },
    {
      "chunk_idx": 25,
      "text": "시의 스트로크 (STROKE)량을 측정하여 표(3)과 같은 기록서를 작성해 두면 이후의 보수에\n편리 하므로 꼭 실시해 주시기 바랍니다.\n7/11 CUSTOMER SHEET NO\n운전 및 유지보수 지침서\nGS 건설 8 OF 11\n표(3)\n측 정 누적 누적\n신율 비고\n년월일 가동 Hr 수송량\n2.5 체인 길이의 조정\n테이크 업(TAKE-UP)의 스트로크( STROKE)가 하한에 이르게 되면 체인(CHAIN)의 길이를 조정하십시오.\n체인의 길이를 단축시키는 경우의 요령은 다음과 같습니다. 체인은 내부 링크(LINK)와 외부 링크가\n번갈아 연결되어 있으므로 외부 링크 (또는 내부 링크)만 떼어낼 수 없습니다. 다음의 연결을 고려하여\n반드시 내외 링크 를 1세트(SET)로 하여 떼어내십시오.\n2.6 윤활요령.\nVENDOR PRINT 12항의LUBRICANTS LIST 참조\n2.7 소모부품\n가동 초기에 소모부품을 상비할 필요는 없으나, 수명은 수송물의 성질,설치보전 상태 등에 의해 동일하지는\n않습니다. 사용자의 체험이나 통상 점검에서 판단해 소모품을 별도 조달 하도록 되어 있습니다.\n대부분의 소모부품은 표와 같으나 형식 및 비고 공란에 대해서는 플로우 콘베어 (FLOW CONVEYOR)의\n납품도에 기재되어 있는 내용을 옮겨 써 놓으면 이후의 관 리에 편리하리라 생각합니다.\n수량\n부 품 명 칭 메이커 형 식 사용부분 비 고\n/1대\n콘베어 체인(CONVEYOR CHAIN) K.C LINK\n헤드케이스\n헤드 스프로켓(HEAD SPROCKET) K.C\n( HEAD CASE)\n테일케이스\n테일 스프로켓(TAIL SPROCKET) K.C\n(TAIL CASE)\n구동용 전동 체인(CHAIN) K.C RS LINK 구동부\n구동용\n주축측 K.C RS 개\n스프로켓 구동부\n모터(MOTOR)측 K.C RS 개\n(SPROCKET)\n베어링 주 축 개 헤드케이스\n(BEARING) 종 축 개 테일케이스\n8/11",
      "header": "CUSTOMER SHEET NO",
      "section_type": "점검",
      "equipment": [
        "비산재처리"
      ],
      "company_id": "14",
      "company_name": "비산재 처리설비",
      "source_file": "16. 운전 및 유지관리 지침서",
      "source_path": "D:\\기계도면\\기계도면\\14. 비산재 처리설비 (조선내화E)\\비산재 준공도서\\비산재(기계)\\16. 운전 및 유지관리 지침서(●)\\16. 운전 및 유지관리 지침서.pdf",
      "rev": "AS_BUILT",
      "chunk_hash": "1f220cec7628d33a",
      "char_count": 947
    },
    {
      "chunk_idx": 26,
      "text": "로켓 구동부\n모터(MOTOR)측 K.C RS 개\n(SPROCKET)\n베어링 주 축 개 헤드케이스\n(BEARING) 종 축 개 테일케이스\n8/11",
      "header": "CUSTOMER SHEET NO",
      "section_type": "일반",
      "equipment": [
        "비산재처리"
      ],
      "company_id": "14",
      "company_name": "비산재 처리설비",
      "source_file": "16. 운전 및 유지관리 지침서",
      "source_path": "D:\\기계도면\\기계도면\\14. 비산재 처리설비 (조선내화E)\\비산재 준공도서\\비산재(기계)\\16. 운전 및 유지관리 지침서(●)\\16. 운전 및 유지관리 지침서.pdf",
      "rev": "AS_BUILT",
      "chunk_hash": "d5db77941ae2ac25",
      "char_count": 80
    },
    {
      "chunk_idx": 27,
      "text": "로켓 구동부\n모터(MOTOR)측 K.C RS 개\n(SPROCKET)\n베어링 주 축 개 헤드케이스\n(BEARING) 종 축 개 테일케이스\n8/11 CUSTOMER SHEET NO\n운전 및 유지보수 지침서\nGS 건설 9 OF 11\n점검시기 불량시의\n점검 항목 점검부분 점검방법 판정기준 결과\nA B C D 조정요령\n테 테일 스프로켓 햄머로 가볍게\n1 고정용 키의 느슨해짐 ○ 보수\n일 (TAIL SPROCKET)의 보스부 두르려본다.\n셋볼트(SET BOLT)의 테일 스프로켓 6각 렌치로 볼트를\n스 2 느슨해짐 ○ (TAIL SPROCKET)의 보스부 돌려본다 보수\n프 링크 플레이트(LINK\n로 관찰 -PLATE)와 테일\n켓 3 중심의 좌우 비틀림 ○ 테일 스프로켓 종축 (불량으로 보이면 측정) 스프로켓이 한쪽만 보수\n닿지 않을것\n체인(CHAIN)의\n1 3.3항 3.4항 참조\n장력상태\n여러 링크(LINK)의\n피치 길이를 측정해 원인 조사후에\n콘 2 피치(PITCH)신장 ○ 체인 본체 평균을 내서 1링크 호칭 피치의 2%이내 체인교체\n베 당의 피치를 산출\n어\n3 수송물의 고착 ○ 중간부의 점검장 관찰 체인 전체청소\n체 헤드.테일(HEAD TAIL)의 굴곡이 유연한가를 불량한 곳의\n4 체인 본체의 굴곡 ○ 관찰\n인 점검창 확인한다. 교체 또는 급유\n체인 보수\n5 부식 ○ 중간부의 점검창 관찰\n또는 교체\n어태치먼트\n6 (ATTACHMENT)의 ○ 중간부의 점검창 관찰 보수\n변형(휩)\n버니어켈리퍼스로 측정\n(롤러의 살두께를 구해 마모에 의하여 일부의\n7 롤러(ROLLER)의 마모 ○ 처음의 살두께와 비교 구멍이 뚫리든가 롤러만 교체\n해서 수명을 추정) 균열이 생길때까지\n롤러살두께=1/2(D-d-f)\n체인 전체를\n버니어켈리퍼스로측정 B=A/3까지\n교체\n8 링크 플레이트의 마모 ○\n체인 전체를\n버니어켈리퍼스로측정 B = 1/2 ≒ H/8까지\n교체\n버니어켈리퍼스로측정\n부쉬 링크만\n(부쉬의 살두께를 구 마모에의하여 일부의\n9 부쉬(BUSH)의 마모 ○ 부쉬 교체 또는 체인\n해 처음의 살 두께와 구멍이 생길때까지\n전체를 교체\n비교하여 수명을측정)\n체인을 분해하여 버니\n어켈리퍼스로 측정\n10 핀(PIN)의 마모 ○ (핀 직경을 구해서 처 B=0.3A 핀만 교체\n음의 직경과 비교해\n수명을 추정)\n1 처짐량 ○ 콘넥스(CONVER)로 측정 =4/100L이 최적 조정\n전\n동\n체 여러 링크의 피치 길이를 호징 피치의\n인 2 피치 신장 ○ 전동 체인 측정해 평균을 내서 1.52%까지 전동 체인 교체\n1링크당의 피치를 산출\n3 급유 3.7항 참조\n이상상태(얹히는것 전동 스프로켓\n전\n1 치저의 마모 ○ 치형 관찰 등)가 발생할때까지를 (SPROCKET)\n동\n기준한다. 교체\n스\n햄머로 가볍게 두드려\n프 2 키의 느슨해짐 ○ 스프로켓의 보스부 보수\n타진해본다\n로\n관찰\n켓 3 중심의 좌우 비틀림 ○ ≤1.5mm 보수\n(불량으로 보이면 측정)\n9/11",
      "header": "CUSTOMER SHEET NO",
      "section_type": "점검",
      "equipment": [
        "비산재처리"
      ],
      "company_id": "14",
      "company_name": "비산재 처리설비",
      "source_file": "16. 운전 및 유지관리 지침서",
      "source_path": "D:\\기계도면\\기계도면\\14. 비산재 처리설비 (조선내화E)\\비산재 준공도서\\비산재(기계)\\16. 운전 및 유지관리 지침서(●)\\16. 운전 및 유지관리 지침서.pdf",
      "rev": "AS_BUILT",
      "chunk_hash": "09b1346c97085e06",
      "char_count": 1425
    },
    {
      "chunk_idx": 28,
      "text": "키의 느슨해짐 ○ 스프로켓의 보스부 보수\n타진해본다\n로\n관찰\n켓 3 중심의 좌우 비틀림 ○ ≤1.5mm 보수\n(불량으로 보이면 측정)\n9/11 CUSTOMER SHEET NO\n운전 및 유지보수 지침서\nGS 건설 10 OF 11\n4.0 트러블의(TROUBLE) 처치요령\n폐사의 콘베어(CONVEYOR)는 품질의 안정된 상품의 완성에 노력하여 항상 엄중한 품질관리 하에\n상품을 출하하고 있습니다.\n콘베어의 수명은 그 사용하는 방법에 따라 수명이 단축되고 생각지도 않은 트러블(TROUBLE)을\n일으키기도 합니다. 또 트러블을 일으켰을 때의 처리 방법에 따라서도 콘베어의 기능에 커다란 차이가\n생겨납니다. 많은 경우 콘베어의 트러블은 단순한 원인에 의한 것입니다.\n그러므로 여기에 몇 가지 콘베어 사고의 예와 그 대책에 대해 기록 하였습니다.\n만약 트러블 발생시 하기의 처지 요령으로 처지후에도 개선되지 않거나, 트러블의 원인을 밝혀 낼 수\n없는 경우에는 무리한 처치나 사용을 하지말고 본사 및 각 지방 영업소에 상담하여 주십시오.\n구분 문 제 점 추 정 원 인 조 사 부 분 처치(대책)\n계량방법 1 계량착오 계량기\n수 투 입 량 2 전접기의 용량부족 전접기 확인 직접기의 능력증대\n송\n수송물에 따라서는 속도를\n용 3 수송물의 비중이 너무 낮다 비중의 측정\n증가시킨다(5~10%)\n량 수송물의 성질\n의\n4 수송물이 투입슈트(CHUTE)에 부착 부착정도확인 정기적으로 부착물 제거\n부\n출력축회전수 속도기 변경(전동 스프로켓\n족 5 체인 속도가 느림(속도비의 선정 착오)\n감속기 (SPROCKET)교체)\n사 양\n수송 속도를 낮춘다\n6 투입 효율이 나쁨(셔터(SHUTTER)효과) 버켓내의 재하상태확인\n(약 5~10%)\n1 후접기의 능력부족(배출 슈트가 막힘) 배출슈트 후접기의 능력 증가\n수\n송 배 출 량 2 후접 탱크(TANK)가 꽉참(배출 슈트가 배출슈트 콘베어 일시 정지\n물 막힘)\n이 수송물의 성질 3 수송물이 버켓내에 부착 부착량 확인 정기적으로 부착물을 제거\n되\n돌 4 배출구(배출",
      "header": "CUSTOMER SHEET NO",
      "section_type": "정지",
      "equipment": [
        "탱크"
      ],
      "company_id": "14",
      "company_name": "비산재 처리설비",
      "source_file": "16. 운전 및 유지관리 지침서",
      "source_path": "D:\\기계도면\\기계도면\\14. 비산재 처리설비 (조선내화E)\\비산재 준공도서\\비산재(기계)\\16. 운전 및 유지관리 지침서(●)\\16. 운전 및 유지관리 지침서.pdf",
      "rev": "AS_BUILT",
      "chunk_hash": "ce737d2cda2e213b",
      "char_count": 999
    },
    {
      "chunk_idx": 29,
      "text": "돌 4 배출구(배출 슈트가 작음) 배출 슈트 배출구(슈트(를 크게\n아 사 양\n옴 5 슈트의 미끄러짐 각이 부족 배출 슈트 슈트각 검토\n10/11",
      "header": "CUSTOMER SHEET NO",
      "section_type": "일반",
      "equipment": [
        "비산재처리"
      ],
      "company_id": "14",
      "company_name": "비산재 처리설비",
      "source_file": "16. 운전 및 유지관리 지침서",
      "source_path": "D:\\기계도면\\기계도면\\14. 비산재 처리설비 (조선내화E)\\비산재 준공도서\\비산재(기계)\\16. 운전 및 유지관리 지침서(●)\\16. 운전 및 유지관리 지침서.pdf",
      "rev": "AS_BUILT",
      "chunk_hash": "133dc8569d824444",
      "char_count": 80
    },
    {
      "chunk_idx": 30,
      "text": "돌 4 배출구(배출 슈트가 작음) 배출 슈트 배출구(슈트(를 크게\n아 사 양\n옴 5 슈트의 미끄러짐 각이 부족 배출 슈트 슈트각 검토\n10/11 CUSTOMER SHEET NO\n운전 및 유지보수 지침서\nGS 건설 11 OF 11\n구분 문 제 점 추 정 원 인 조 사 부 분 처치(대책)\n그랜드패킹(GLAND PACKING)의\n1 주축,종축의 방진판 주축.종축부 체질 볼트(BOLT)를 더 조이거나,\n교체\n체 결 부\n케이스(CASE)의 체결 볼트를 더 조이거나\n2 각 플랜지부\n전체 실(SEAL)제를 도포한다.\n먼\n3 패킹(PACKING)손상 케이스 전체 보수 또는 교체\n지\n의\n운전방법 4 큰 낙차에 의한 투입압력 증대 투입방법 쿠선 탱크(CUSHION TANK)등 취부\n누\n설 수송물의 입자경이 작거나 미분알 상태로\n5 각부틈새 패킹부착 또는 실제 도포\n성질 틈새에서 누설\n전접기가 에어 슬라이드(AIR SLIDE)등으\n내 압 6 전접부 에어(AIR)제거 장치를 부착\n로 내압이 걸림\n구 동 원 1 모터(MOTOR)의 회전불량(고장) 모터 수리 또는 교체\n유체 커플링(COUPLING)의 경우\n모터. 커플링.감속기의 중심잡기, 키\n2 모터 베이스 재조정\n(KEY)맞춤, 고정법(사몹퍼(STOPPER),\n모 녹핀(KNOCK PIN)의 불량\n터 중십잡기\n모터 베이스(MOTOR BASE)의 중심잡기 및 수평상태\n베 3 모터 베이스 재조정\n불량\n이\n스 4 전동 스프로켓의 중심불량 중심잡기 재조정\n의\n진 강 도 5 강도 부족 보강\n동\n치 형 6 헤드.테일 스프로켓(HEAD.TAIL SPROCKET)의 치형 불량 치형 수정\n전동체인 7 전동 체인의 늘어짐 길이를 알맞게 조정\n테일 케이스(TAIL CASE).밀판과 체인(CHAIN)의 길이 조정,\n1 테일 케이스\n버켓(BUCKET)의 접촉 테이크 업 조정\n2 가이드(GUIDE)판과 버켓의 접촉 테일 케이스 가이드 판 보수\n접 촉 주축, 종축의 키(KEY)가 느슨해져 스프\n스프로켓 위치 조정, 셋 볼트를\n마 3 로켓(SPROCKET)이 이동하여 체인 주축, 종축\n더 조임\n찰 (CHAIN)과 레일(RAIL)이 접촉\n음\n4 레일이 변형하여 레일과 체인 접촉 케이스(CASE) 전체 레일 중심잡기\n이 가이드 판과 버켓 사이에 수송물이\n물러들기 5 테일 케이스 투입 각도를 크게\n상 물려 들어감\n음\n발 회전불량 6 베어링(BEARING), 회전불량 베어링 베어링 교체\n생 드라이브(DRIVE)\n물러들기 1 이물질, 수송물 덩어리가 테일 케이스내에 물려 들어감 계통 전반,테일 이물질 등을 제거하여 수리\n케이스 캠 클러치\n헤드 스프로켓(HEAD SPROCKET), 테일\n충 2 스프로켓(TAIL SPROCKET)의 치형의 변경 스프로켓 치형 수정 또는 스프로켓 교환\n치 형\n격\n음 3 헤드 스프로켓과 체인의 떨어짐이 나쁘다 헤드 스프로켓 치형 수정\n전동 체인의\n전동체인 4 전동 체인의 공회전 전동 체인의 길이 조정\n장력상태\n조립, 설치 5 부속부품(레일등)의 취부 위치가 불량 케이스 전체 보수\n11/11",
      "header": "CUSTOMER SHEET NO",
      "section_type": "점검",
      "equipment": [
        "탱크"
      ],
      "company_id": "14",
      "company_name": "비산재 처리설비",
      "source_file": "16. 운전 및 유지관리 지침서",
      "source_path": "D:\\기계도면\\기계도면\\14. 비산재 처리설비 (조선내화E)\\비산재 준공도서\\비산재(기계)\\16. 운전 및 유지관리 지침서(●)\\16. 운전 및 유지관리 지침서.pdf",
      "rev": "AS_BUILT",
      "chunk_hash": "57c187a4d679b307",
      "char_count": 1482
    }
  ]
}